dewi/__init__.py
dewi/__main__.py
dewi-2.3.1.dist-info/COPYING
dewi-2.3.1.dist-info/METADATA
dewi-2.3.1.dist-info/WHEEL
dewi-2.3.1.dist-info/entry_points.txt
dewi-2.3.1.dist-info/top_level.txt
dewi-2.3.1.dist-info/zip-safe
dewi-2.3.1.dist-info/RECORD
